entelligence_cli/__init__.py
entelligence_cli/api_client.py
entelligence_cli/ascii-art.txt
entelligence_cli/cli.py
entelligence_cli/config.py
entelligence_cli/exceptions.py
entelligence_cli/git_operations.py
entelligence_cli/textual_ui.py
entelligence_cli/update_checker.py
entelligence_cli/commands/__init__.py
entelligence_cli/commands/auth.py
entelligence_cli/commands/review.py
entelligence_cli/ui/__init__.py
entelligence_cli/ui/interactive.py
entelligence_cli/ui/loaders.py
entelligence_cli/ui/output.py
entelligence_cli/ui/styles.py
entelligence_cli-0.1.16.dist-info/METADATA
entelligence_cli-0.1.16.dist-info/WHEEL
entelligence_cli-0.1.16.dist-info/entry_points.txt
entelligence_cli-0.1.16.dist-info/top_level.txt
entelligence_cli-0.1.16.dist-info/RECORD
