Metadata-Version: 2.4
Name: entelligence-cli
Version: 0.1.16
Summary: AI-powered code review assistant for your terminal - Get instant, intelligent feedback on your code changes
Author-email: EntelligenceAI <info@entelligence.ai>
Project-URL: Homepage, https://entelligence.ai
Project-URL: Documentation, https://docs.entelligence.ai
Keywords: code-review,ai,artificial-intelligence,cli,git,code-analysis,developer-tools,productivity,entelligence
Classifier: Development Status :: 4 - Beta
Classifier: Intended Audience :: Developers
Classifier: Topic :: Software Development :: Quality Assurance
Classifier: Topic :: Software Development :: Code Generators
Classifier: Programming Language :: Python :: 3
Classifier: Programming Language :: Python :: 3.9
Classifier: Programming Language :: Python :: 3.10
Classifier: Programming Language :: Python :: 3.11
Classifier: Programming Language :: Python :: 3.12
Classifier: Programming Language :: Python :: 3.13
Classifier: Environment :: Console
Classifier: Operating System :: OS Independent
Requires-Python: >=3.9
Requires-Dist: click>=8.0.0
Requires-Dist: requests>=2.28.0
Requires-Dist: rich>=13.0.0
Provides-Extra: dev
Requires-Dist: pytest>=8.0.0; extra == "dev"
Requires-Dist: ruff>=0.8.0; extra == "dev"
Requires-Dist: pytest-cov>=5.0.0; extra == "dev"
